{"name": "1992년_설립된_스포츠_리그", "id": 1021267, "predecessors": [{"name": "단체_스포츠", "id": 2981973}, {"name": "1992년_설립된_단체", "id": 1730568}], "successors": [{"name": "프리미어리그_시즌", "id": 1075272}, {"name": "프리미어리그의_축구_선수", "id": 1121929}, {"name": "프리미어리그_구단", "id": 1189983}, {"name": "프리미어리그의_축구_감독", "id": 1493054}, {"name": "J1리그의_축구_감독", "id": 1656584}, {"name": "J1리그_구단", "id": 3746067}, {"name": "프르바_HNL의_축구_선수", "id": 1986345}, {"name": "우즈베키스탄_슈퍼리그의_축구_선수", "id": 1986356}, {"name": "비르스리가의_축구_선수", "id": 3633897}, {"name": "NK_자그레브의_축구_선수", "id": 551274}, {"name": "NK_오시예크의_축구_선수", "id": 1446443}, {"name": "로코모티프_타슈켄트의_축구_선수", "id": 1320938}, {"name": "파흐타코르_타슈켄트_FK의_축구_선수", "id": 2939233}]}