{"name": "도시", "id": 11363, "predecessors": [{"name": "도시지리학", "id": 289089}, {"name": "사회_집단", "id": 289990}], "successors": [{"name": "수도", "id": 38607}, {"name": "도시_계획", "id": 89153}, {"name": "도시국가", "id": 605963}, {"name": "분단된_도시", "id": 899788}, {"name": "도심_황폐화", "id": 1421161}, {"name": "인구순_도시_목록", "id": 406267}, {"name": "파괴된_도시", "id": 1013591}, {"name": "하계_올림픽_개최_도시", "id": 631230}, {"name": "동계_올림픽_개최_도시", "id": 632622}, {"name": "네덜란드의_도시", "id": 14258}, {"name": "루마니아의_도시", "id": 15257}, {"name": "벨기에의_도시", "id": 27955}, {"name": "덴마크의_도시", "id": 27956}, {"name": "스웨덴의_도시", "id": 30005}, {"name": "노르웨이의_도시", "id": 30240}, {"name": "다뉴브강_주변_도시", "id": 158014}, {"name": "유럽에_위치한_수도", "id": 972911}, {"name": "인도네시아의_도시", "id": 55079}, {"name": "아시아에_위치한_수도", "id": 972888}, {"name": "탄자니아의_도시", "id": 71271}, {"name": "아프리카에_위치한_수도", "id": 972907}, {"name": "프랑스의_코뮌_목록", "id": 656621}, {"name": "그뢰나선", "id": 700454}, {"name": "스톡홀름_지하철역", "id": 3605967}, {"name": "프랑스의_항구_도시", "id": 774207}, {"name": "독일의_항구_도시", "id": 774224}, {"name": "이탈리아의_항구_도시", "id": 774225}, {"name": "영국의_항구_도시", "id": 774226}, {"name": "튀르키예의_항구_도시", "id": 774333}, {"name": "러시아의_항구_도시", "id": 774334}, {"name": "그리스의_항구_도시", "id": 774335}, {"name": "스페인의_항구_도시", "id": 774350}, {"name": "노르웨이의_항구_도시", "id": 774367}, {"name": "흑해의_항구_도시", "id": 1488442}, {"name": "아드리아해의_항구_도시", "id": 1488444}, {"name": "루마니아의_항구_도시", "id": 1488459}, {"name": "발트해의_항구_도시", "id": 1488521}, {"name": "북해의_항구_도시", "id": 1488526}, {"name": "일본의_항구_도시", "id": 708287}, {"name": "대한민국의_항구_도시", "id": 774210}, {"name": "중국의_항구_도시", "id": 774218}, {"name": "인도의_항구_도시", "id": 774339}, {"name": "필리핀의_항구_도시", "id": 1488458}, {"name": "홍콩의_기업", "id": 100296}, {"name": "몬젠마치", "id": 1948189}, {"name": "조카마치", "id": 2692325}, {"name": "룩셈부르크의_도시", "id": 34513}, {"name": "원산시", "id": 42881}, {"name": "정주시_출신", "id": 1289435}, {"name": "서울특별시의_스포츠", "id": 83522}, {"name": "대전광역시의_스포츠", "id": 102669}, {"name": "인천광역시의_스포츠", "id": 104439}, {"name": "부산광역시의_스포츠", "id": 110489}, {"name": "대구광역시의_스포츠", "id": 110490}, {"name": "창원시의_스포츠", "id": 681691}, {"name": "고양시의_스포츠", "id": 699599}, {"name": "시카고_컵스", "id": 470670}, {"name": "샌프란시스코_자이언츠", "id": 103845}, {"name": "세인트루이스_카디널스", "id": 108696}, {"name": "요코하마시의_스포츠", "id": 110177}, {"name": "FC_바이에른_뮌헨", "id": 166817}, {"name": "페예노르트의_축구_선수", "id": 316226}, {"name": "페예노르트의_축구_감독", "id": 399701}, {"name": "런던의_스포츠", "id": 104202}, {"name": "모스크바_출신_스포츠인", "id": 3164746}, {"name": "AIK_포트볼의_축구_선수", "id": 393583}, {"name": "산투스_FC의_축구_선수", "id": 329523}, {"name": "AS_리보르노_칼초의_축구_선수", "id": 396859}, {"name": "CD_테네리페의_축구_선수", "id": 369512}, {"name": "CD_테네리페의_축구_감독", "id": 399620}, {"name": "던디_FC의_축구_선수", "id": 526489}, {"name": "US_살레르니타나_1919의_축구_선수", "id": 945015}, {"name": "UD_레이리아의_축구_선수", "id": 385345}, {"name": "HNK_리예카의_축구_선수", "id": 957123}, {"name": "SKA_상트페테르부르크_선수", "id": 1259490}, {"name": "아크_바르스_카잔_선수", "id": 1259498}, {"name": "루턴_타운_FC의_축구_선수", "id": 1226083}, {"name": "INAC_고베_레오네사의_축구_선수", "id": 2483658}, {"name": "니시테쓰_라이온스_선수", "id": 242216}, {"name": "BG_빠툼_유나이티드_FC의_축구_선수", "id": 1446727}, {"name": "구정컵", "id": 1035589}, {"name": "2008년_하계_올림픽", "id": 62908}, {"name": "베네치아_FC의_축구_선수", "id": 944320}, {"name": "서울특별시청", "id": 747994}, {"name": "광주광역시청", "id": 756346}, {"name": "전북특별자치도청", "id": 756355}, {"name": "제주특별자치도청", "id": 792080}, {"name": "강원특별자치도청", "id": 797354}, {"name": "경상남도청", "id": 826825}, {"name": "경기도청", "id": 850035}, {"name": "대구광역시청", "id": 855191}, {"name": "부산광역시청", "id": 855567}, {"name": "인천광역시청", "id": 862486}, {"name": "전라남도청", "id": 875891}, {"name": "경상북도청", "id": 879467}, {"name": "충청남도청", "id": 880846}, {"name": "대전광역시청", "id": 881899}, {"name": "대한민국의_시도청_소재지", "id": 3780955}, {"name": "도시명_변경", "id": 3226638}, {"name": "FC_프로_베르첼리_1892의_축구_선수", "id": 3327445}, {"name": "모스크바의_건축물", "id": 223582}, {"name": "모스크바_출신", "id": 651358}, {"name": "상트페테르부르크_출신", "id": 651353}, {"name": "타오위안시_출신", "id": 659039}, {"name": "가오슝시의_행정_구역", "id": 491685}, {"name": "가오슝시_출신", "id": 651365}, {"name": "타이베이시의_건축물", "id": 538704}, {"name": "타이베이시_출신", "id": 584500}, {"name": "타이베이시의_역사", "id": 599242}, {"name": "타이난시의_행정_구역", "id": 599997}, {"name": "타이난시_출신", "id": 659032}, {"name": "타이중시의_행정_구역", "id": 599985}, {"name": "타이중시_출신", "id": 659031}, {"name": "신베이시의_행정_구역", "id": 599852}, {"name": "신베이시_출신", "id": 659030}, {"name": "가오슝_첩운_귤선", "id": 1133671}, {"name": "가오슝_첩운_홍선", "id": 1133677}, {"name": "상트페테르부르크의_구", "id": 65763}, {"name": "타이베이_첩운의_철도역", "id": 713952}, {"name": "모스크바의_기업", "id": 2673143}, {"name": "정령지정도시", "id": 45584}, {"name": "인천광역시", "id": 6026}, {"name": "부산광역시", "id": 6031}, {"name": "대구광역시", "id": 6078}, {"name": "광주광역시", "id": 6087}, {"name": "대전광역시", "id": 6121}, {"name": "세종특별자치시", "id": 652853}, {"name": "평양시", "id": 32908}, {"name": "개성시", "id": 89815}, {"name": "남포시_출신", "id": 994828}, {"name": "알마티_출신", "id": 1021538}, {"name": "대전광역시의_축구단", "id": 1187631}, {"name": "울산광역시의_축구단", "id": 1187637}, {"name": "서울특별시의_축구단", "id": 1187640}, {"name": "광주광역시의_축구단", "id": 1187874}, {"name": "대구광역시의_축구단", "id": 1187965}, {"name": "인천광역시의_축구단", "id": 1188005}, {"name": "제주시의_축구단", "id": 1188111}, {"name": "창원시의_축구단", "id": 1188202}, {"name": "수원시의_축구단", "id": 1188331}, {"name": "부산광역시의_축구단", "id": 1188337}, {"name": "평양시의_축구단_(대한민국)", "id": 3756912}, {"name": "전북_현대_모터스", "id": 120361}, {"name": "서울특별시의_야구단", "id": 3685668}, {"name": "서울특별시의_정구단", "id": 3754085}, {"name": "서울특별시의_육상단", "id": 3830150}, {"name": "GS칼텍스_서울_KIXX의_선수", "id": 2385068}, {"name": "평양시의_축구단", "id": 1189518}, {"name": "고대_도시", "id": 661424}, {"name": "한자_동맹_가맹도시", "id": 1376645}, {"name": "카타르_SC의_축구_선수", "id": 543139}, {"name": "알아라비_(카타르)의_축구_선수", "id": 611445}, {"name": "알가라파_SC의_축구_선수", "id": 611471}, {"name": "알사드_SC의_축구_선수", "id": 611476}, {"name": "알아흘리_(도하)의_축구_선수", "id": 1227280}, {"name": "알사일리야_SC의_축구_선수", "id": 1368920}, {"name": "알두하일_SC의_축구_선수", "id": 2456113}, {"name": "바라칼도_CF의_축구_선수", "id": 2885420}, {"name": "자그웽비에_루빈의_축구_선수", "id": 1598369}, {"name": "토론토의_철도역", "id": 751446}, {"name": "서울특별시의_터널", "id": 226335}]}