{"name": "환경", "id": 12071, "predecessors": [{"name": "지구", "id": 30580}, {"name": "사이버네틱스", "id": 100576}], "successors": [{"name": "기후", "id": 27946}, {"name": "지속_가능성", "id": 32509}, {"name": "도시_계획", "id": 89153}, {"name": "지하공간", "id": 571991}, {"name": "환경공학", "id": 685322}, {"name": "환경_디자인", "id": 692021}, {"name": "공해", "id": 42224}, {"name": "수질_오염", "id": 151118}, {"name": "환경_논란", "id": 821744}, {"name": "기후_변화의_영향", "id": 959416}, {"name": "인간에게_절멸된_종", "id": 1423956}, {"name": "지속_가능한_기술", "id": 704382}, {"name": "집단생태학", "id": 935009}, {"name": "기후_변화", "id": 137277}, {"name": "IUCN_카테고리_II", "id": 300236}, {"name": "대한민국의_국립공원", "id": 23263}, {"name": "일본의_국립공원", "id": 55393}, {"name": "중화인민공화국의_국립공원", "id": 295899}, {"name": "세계_최악의_100대_침입외래종", "id": 3601997}, {"name": "EDGE_종", "id": 1770797}, {"name": "IUCN_적색_목록_절멸종", "id": 943092}, {"name": "대한민국_환경부", "id": 657387}]}