{"name": "국제_관계", "id": 12141, "predecessors": [{"name": "정치지리학", "id": 23349}, {"name": "사회", "id": 31673}, {"name": "공공_정책", "id": 635024}, {"name": "문화_세계화", "id": 1423312}], "successors": [{"name": "전쟁", "id": 11891}, {"name": "국제_기구", "id": 11959}, {"name": "평화", "id": 12142}, {"name": "냉전", "id": 23037}, {"name": "국제_무역", "id": 34129}, {"name": "국제법", "id": 34130}, {"name": "외교", "id": 44082}, {"name": "국제관계사", "id": 54311}, {"name": "국제방송", "id": 89977}, {"name": "세계화", "id": 198757}, {"name": "난민", "id": 215150}, {"name": "지정학", "id": 415664}, {"name": "국제_회의", "id": 479483}, {"name": "국제_교류", "id": 579355}, {"name": "민족통일주의", "id": 579371}, {"name": "외무부", "id": 658440}, {"name": "국제안보", "id": 670486}, {"name": "주권", "id": 1104927}, {"name": "국제_개발", "id": 1104971}, {"name": "세계정부", "id": 1269876}, {"name": "대안세계화", "id": 1475059}, {"name": "외교_사건", "id": 1742106}, {"name": "고립주의", "id": 2498201}, {"name": "국제_교량", "id": 651155}, {"name": "영토_분쟁", "id": 35675}, {"name": "16세기_분쟁", "id": 247693}, {"name": "17세기_분쟁", "id": 466962}, {"name": "20세기_분쟁", "id": 466965}, {"name": "7세기_분쟁", "id": 1430589}, {"name": "기원전_3세기_분쟁", "id": 1477218}, {"name": "기원전_4세기_분쟁", "id": 1477219}, {"name": "기원전_5세기_분쟁", "id": 1477220}, {"name": "2020년_국제_관계", "id": 2618978}, {"name": "2021년_국제_관계", "id": 2917555}, {"name": "2022년_국제_관계", "id": 3145686}, {"name": "2023년_국제_관계", "id": 3581237}, {"name": "2024년_국제_관계", "id": 3720738}, {"name": "대한민국의_반일_감정", "id": 1464099}, {"name": "분할_(정치)", "id": 717202}, {"name": "페레스트로이카", "id": 764000}, {"name": "구소련_분쟁", "id": 1884704}, {"name": "조선민주주의인민공화국에_대한_제재", "id": 3167927}, {"name": "러시아의_항공사", "id": 58779}, {"name": "독일의_항공사", "id": 74768}, {"name": "프랑스의_항공사", "id": 80176}, {"name": "영국의_항공사", "id": 120547}, {"name": "일본의_철도_기업", "id": 107183}, {"name": "대한민국의_철도_기업", "id": 107187}, {"name": "우크라이나의_역사", "id": 38341}, {"name": "우크라이나의_기업인", "id": 506603}, {"name": "우크라이나의_민족", "id": 41973}, {"name": "우크라이나의_언어", "id": 407456}, {"name": "유로마이단", "id": 1052621}, {"name": "크림_위기", "id": 1070484}, {"name": "2014년_우크라이나_친러시아_분쟁", "id": 1086219}, {"name": "ITU-T_권고", "id": 908036}, {"name": "ISO_표준", "id": 15003}, {"name": "W3C_표준", "id": 15004}, {"name": "IEEE_표준", "id": 28115}, {"name": "IEC_표준", "id": 449082}, {"name": "3GPP_표준", "id": 1985082}, {"name": "Ecma_표준", "id": 2712032}, {"name": "한국_전쟁을_소재로_한_작품", "id": 788041}, {"name": "남북_관계를_소재로_한_영화", "id": 1722761}, {"name": "18세기_반란", "id": 3639111}, {"name": "19세기_반란", "id": 3639112}, {"name": "20세기_혁명", "id": 885583}, {"name": "21세기_혁명", "id": 1062828}, {"name": "유엔_총회_의장", "id": 428306}, {"name": "유엔_주재_대한민국_대사", "id": 1385268}, {"name": "유엔_주재_미국_대사", "id": 1392352}]}