{"name": "박물관", "id": 13515, "predecessors": [{"name": "공공_서비스", "id": 395659}, {"name": "인문학", "id": 172058}, {"name": "교육", "id": 11817}, {"name": "문화_단체", "id": 646637}, {"name": "건축물", "id": 28224}], "successors": [{"name": "할리우드_명예의_거리", "id": 199169}, {"name": "과학기술인_명예의_전당", "id": 297044}, {"name": "인터넷_명예의_전당", "id": 1365172}, {"name": "국립_박물관", "id": 580833}, {"name": "야외_박물관", "id": 612187}, {"name": "인물_박물관", "id": 829222}, {"name": "고택_박물관", "id": 3212944}, {"name": "박물관장", "id": 1403205}, {"name": "박물관_설립자", "id": 2047660}, {"name": "서울_도심", "id": 3741033}, {"name": "스미스소니언_협회", "id": 686657}, {"name": "2005년_설립된_박물관", "id": 2550492}, {"name": "1993년_설립된_박물관", "id": 3821971}, {"name": "2001년_설립된_박물관", "id": 3821974}, {"name": "2004년_설립된_박물관", "id": 3821975}, {"name": "1998년_설립된_박물관", "id": 3821998}, {"name": "2002년_설립된_박물관", "id": 3822001}, {"name": "2003년_설립된_박물관", "id": 3822002}, {"name": "2007년_설립된_박물관", "id": 3822005}, {"name": "2012년_설립된_박물관", "id": 3822009}, {"name": "2013년_설립된_박물관", "id": 3822010}, {"name": "2008년_설립된_박물관", "id": 3822052}]}