{"name": "경기도의_도시", "id": 1363197, "predecessors": [{"name": "경기도의_지리", "id": 596554}, {"name": "도시", "id": 11363}], "successors": [{"name": "안산시의_교통", "id": 387798}, {"name": "안산시_출신", "id": 603338}, {"name": "안산시의_지리", "id": 662859}, {"name": "안산시의_건축물", "id": 664330}, {"name": "안산시의_무덤", "id": 1953412}, {"name": "안산시의_단체", "id": 2712495}, {"name": "안산시의_정치", "id": 2948476}, {"name": "고양시의_교통", "id": 387762}, {"name": "고양시_출신", "id": 593942}, {"name": "고양시의_건축물", "id": 664317}, {"name": "고양시의_스포츠", "id": 699599}, {"name": "고양시의_역사", "id": 912727}, {"name": "고양시의_무덤", "id": 1931647}, {"name": "고양시의_정치", "id": 2948481}, {"name": "수원시의_교통", "id": 236355}, {"name": "수원시의_건축물", "id": 497169}, {"name": "수원시_출신", "id": 588991}, {"name": "수원시의_지리", "id": 662857}, {"name": "수원시의_단체", "id": 2655805}, {"name": "수원시의_정치", "id": 2945960}, {"name": "부천시의_교통", "id": 387794}, {"name": "부천시_출신", "id": 580203}, {"name": "부천시의_건축물", "id": 664326}, {"name": "부천시의_역사", "id": 912748}, {"name": "부천시의_정치", "id": 2946006}, {"name": "안양시의_교통", "id": 387766}, {"name": "안양시_출신", "id": 593948}, {"name": "안양시의_건축물", "id": 664333}, {"name": "안양시의_단체", "id": 2703541}, {"name": "안양시의_도로", "id": 2882787}, {"name": "안양시의_정치", "id": 2946005}, {"name": "광명시의_교통", "id": 432797}, {"name": "광명시_출신", "id": 603319}, {"name": "광명시의_건축물", "id": 664319}, {"name": "광명시의_정치", "id": 2948455}, {"name": "광주시의_교통", "id": 387775}, {"name": "광주시_(경기도)_출신", "id": 593951}, {"name": "광주시의_건축물", "id": 664320}, {"name": "광주시의_정치", "id": 2948824}, {"name": "이천시의_교통", "id": 387821}, {"name": "이천시_출신", "id": 595997}, {"name": "이천시의_건축물", "id": 664341}, {"name": "이천시의_정치", "id": 2948807}, {"name": "파주시의_교통", "id": 230983}, {"name": "파주시_출신", "id": 593944}, {"name": "파주시의_행정_구역", "id": 663451}, {"name": "파주시의_건축물", "id": 664342}, {"name": "파주시의_역사", "id": 910196}, {"name": "파주시의_무덤", "id": 1958684}, {"name": "파주시의_정치", "id": 2948640}, {"name": "구리시의_교통", "id": 387777}, {"name": "구리시_출신", "id": 603317}, {"name": "구리시의_건축물", "id": 664321}, {"name": "김포시의_교통", "id": 387782}, {"name": "김포시_출신", "id": 608142}, {"name": "김포시의_지리", "id": 662852}, {"name": "김포시의_건축물", "id": 664323}, {"name": "김포시의_역사", "id": 912741}, {"name": "김포시의_정치", "id": 2948823}, {"name": "남양주시의_교통", "id": 387778}, {"name": "남양주시_출신", "id": 604827}, {"name": "남양주시의_지리", "id": 662853}, {"name": "남양주시의_건축물", "id": 664324}, {"name": "남양주시의_무덤", "id": 1931642}, {"name": "남양주시의_정치", "id": 2948586}, {"name": "성남시의_교통", "id": 387756}, {"name": "성남시_출신", "id": 593955}, {"name": "성남시의_지리", "id": 662856}, {"name": "성남시의_건축물", "id": 664328}, {"name": "성남시의_단체", "id": 2655897}, {"name": "성남시의_정치", "id": 2945978}, {"name": "과천시의_교통", "id": 387765}, {"name": "과천시_출신", "id": 603342}, {"name": "과천시의_정치", "id": 2948565}, {"name": "군포시의_교통", "id": 387773}, {"name": "군포시_출신", "id": 604821}, {"name": "군포시의_정치", "id": 2948635}, {"name": "포천시의_교통", "id": 387837}, {"name": "포천시_출신", "id": 603325}, {"name": "포천시의_지리", "id": 662870}, {"name": "포천시의_건축물", "id": 664344}, {"name": "포천시의_무덤", "id": 1931657}, {"name": "포천시의_도로", "id": 2882788}, {"name": "포천시의_정치", "id": 2948825}, {"name": "양주시의_교통", "id": 387812}, {"name": "양주시_출신", "id": 603341}, {"name": "양주시의_건축물", "id": 664336}, {"name": "양주시의_역사", "id": 912759}, {"name": "양주시의_정치", "id": 2948458}, {"name": "평택시의_교통", "id": 290357}, {"name": "평택시_출신", "id": 593945}, {"name": "평택시의_건축물", "id": 664343}, {"name": "평택시의_정치", "id": 2948456}, {"name": "동두천시_출신", "id": 603324}, {"name": "동두천시의_정치", "id": 2948464}, {"name": "의정부시의_교통", "id": 387818}, {"name": "의정부시_출신", "id": 595582}, {"name": "의정부시의_건축물", "id": 664340}, {"name": "의정부시의_정치", "id": 2945983}, {"name": "화성시의_교통", "id": 432800}, {"name": "화성시_출신", "id": 603311}, {"name": "화성시의_지리", "id": 662872}, {"name": "화성시의_행정_구역", "id": 663455}, {"name": "화성시의_건축물", "id": 664346}, {"name": "화성시의_역사", "id": 912773}, {"name": "화성시의_정치", "id": 2948599}, {"name": "시흥시의_교통", "id": 387796}, {"name": "시흥시의_건축물", "id": 664329}, {"name": "시흥시_출신", "id": 911500}, {"name": "시흥시의_정치", "id": 2948616}, {"name": "중앙대학교", "id": 123891}, {"name": "안성시의_교통", "id": 256547}, {"name": "안성시_출신", "id": 603280}, {"name": "안성시의_건축물", "id": 664332}, {"name": "안성시의_도로", "id": 2872855}, {"name": "안성시의_정치", "id": 2948819}, {"name": "오산시의_교통", "id": 254175}, {"name": "오산시_출신", "id": 604823}, {"name": "용인시의_교통", "id": 387817}, {"name": "용인시_출신", "id": 603335}, {"name": "용인시의_지리", "id": 662864}, {"name": "용인시의_행정_구역", "id": 663447}, {"name": "용인시의_건축물", "id": 664338}, {"name": "용인시의_역사", "id": 876996}, {"name": "용인시의_무덤", "id": 1932089}, {"name": "용인시의_도로", "id": 2536508}, {"name": "용인시의_단체", "id": 2676006}, {"name": "용인시의_정치", "id": 2948811}, {"name": "의왕시의_교통", "id": 387772}, {"name": "하남시의_교통", "id": 387840}, {"name": "하남시_출신", "id": 608156}, {"name": "하남시의_건축물", "id": 664345}, {"name": "하남시의_정치", "id": 2948638}, {"name": "경희대학교", "id": 121259}, {"name": "단국대학교", "id": 128944}, {"name": "용인시의_학교", "id": 664585}, {"name": "아주대학교", "id": 164290}, {"name": "수원시의_학교", "id": 664578}, {"name": "고양시의_학교", "id": 664567}, {"name": "성남시의_학교", "id": 664577}, {"name": "한양대학교", "id": 123892}, {"name": "광주시의_법정동", "id": 1589203}, {"name": "부천시의_법정동", "id": 1589197}, {"name": "시흥시의_법정동", "id": 1589209}, {"name": "안성시의_법정동", "id": 1589227}, {"name": "양주시의_법정동", "id": 1589189}, {"name": "오산시의_법정동", "id": 1589225}, {"name": "파주시의_법정동", "id": 1586056}, {"name": "평택시의_법정동", "id": 1589229}, {"name": "하남시의_법정동", "id": 1589199}, {"name": "덕양구", "id": 663734}, {"name": "일산동구", "id": 663735}, {"name": "일산서구", "id": 663745}, {"name": "광명시의_행정동", "id": 1589230}, {"name": "소사구", "id": 663799}, {"name": "원미구", "id": 663804}, {"name": "오정구", "id": 669235}, {"name": "부천시의_행정동", "id": 1589196}, {"name": "분당구", "id": 663807}, {"name": "중원구", "id": 663808}, {"name": "수정구", "id": 663813}, {"name": "성남시의_행정동", "id": 1589200}, {"name": "영통구", "id": 663815}, {"name": "권선구", "id": 663818}, {"name": "팔달구", "id": 663819}, {"name": "장안구", "id": 663821}, {"name": "수원시의_행정동", "id": 1589220}, {"name": "시흥시의_행정동", "id": 1589208}, {"name": "단원구", "id": 663832}, {"name": "상록구", "id": 663833}, {"name": "안산시의_행정동", "id": 1589210}, {"name": "동안구", "id": 663834}, {"name": "만안구", "id": 663835}, {"name": "안양시의_행정동", "id": 1589214}, {"name": "평택시의_행정동", "id": 1589228}, {"name": "과천시_소재의_관공서", "id": 935501}, {"name": "오산시의_아파트", "id": 3604202}, {"name": "군포시의_초등학교", "id": 1185678}, {"name": "오산시의_초등학교", "id": 1186378}, {"name": "안양시의_문화재", "id": 778473}, {"name": "덕양구의_행정동", "id": 1583801}, {"name": "덕양구의_법정동", "id": 1583802}, {"name": "안성시의_문화재", "id": 912757}, {"name": "파주시의_문화재", "id": 910194}, {"name": "광명시의_문화재", "id": 912731}, {"name": "광주시의_문화재", "id": 912733}, {"name": "구리시의_문화재", "id": 912735}, {"name": "남양주시의_문화재", "id": 912742}, {"name": "성남시의_문화재", "id": 912749}, {"name": "수원시의_문화재", "id": 912751}, {"name": "안산시의_문화재", "id": 912755}, {"name": "세월호_침몰_사고", "id": 1089458}, {"name": "의정부시의_문화재", "id": 912764}, {"name": "이천시의_문화재", "id": 912766}, {"name": "평택시의_문화재", "id": 912768}, {"name": "포천시의_문화재", "id": 912770}, {"name": "여주시의_건축물", "id": 991816}, {"name": "여주시의_교통", "id": 993316}, {"name": "여주시_출신", "id": 994245}, {"name": "여주시의_무덤", "id": 1958668}, {"name": "여주시의_정치", "id": 2948801}, {"name": "여주시의_문화재", "id": 993783}, {"name": "시흥시의_향토유적", "id": 1920534}, {"name": "양주시의_문화재", "id": 912758}, {"name": "수원시의_축구단", "id": 1188331}, {"name": "고양시의_문화재", "id": 912726}, {"name": "김포시의_문화재", "id": 912740}, {"name": "용인시의_문화재", "id": 876994}, {"name": "화성시의_문화재", "id": 912772}, {"name": "수원시의_기업", "id": 2655879}, {"name": "화성시의_기업", "id": 3218357}]}