{"name": "정부", "id": 15935, "predecessors": [{"name": "사회", "id": 31673}, {"name": "사회학_이론", "id": 632947}], "successors": [{"name": "선거", "id": 11866}, {"name": "정부형태", "id": 32605}, {"name": "재정", "id": 34296}, {"name": "정책", "id": 103953}, {"name": "법", "id": 130821}, {"name": "사회_보장", "id": 215240}, {"name": "행정학", "id": 313684}, {"name": "공공_정책", "id": 635024}, {"name": "정부_로고", "id": 1579515}, {"name": "국가안전보장", "id": 1656113}, {"name": "입법부", "id": 15936}, {"name": "중앙은행", "id": 128190}, {"name": "공무원", "id": 274279}, {"name": "정당", "id": 11832}, {"name": "망명정부", "id": 281204}, {"name": "나라별_의회", "id": 68824}, {"name": "조선민주주의인민공화국_정부", "id": 473990}, {"name": "베트남_정부", "id": 580864}, {"name": "중화인민공화국_정부", "id": 663809}, {"name": "영국_정부", "id": 683607}, {"name": "프랑스_정부", "id": 805132}, {"name": "일본_정부", "id": 1434678}, {"name": "핀란드_정부", "id": 1556456}, {"name": "미국의_중앙행정관청", "id": 455909}, {"name": "관직", "id": 307068}, {"name": "섭정", "id": 98748}, {"name": "현재_국가_지도자", "id": 670753}, {"name": "암살된_정부수반", "id": 1528531}, {"name": "미국의_대통령_배우자", "id": 171617}, {"name": "일본의_내각총리대신", "id": 11822}, {"name": "미국의_대통령", "id": 12324}, {"name": "영국의_총리", "id": 12688}, {"name": "조선민주주의인민공화국의_총리", "id": 507470}, {"name": "대한민국의_국무총리", "id": 29645}, {"name": "폴란드의_총리", "id": 39284}, {"name": "뉴질랜드의_총리", "id": 44758}, {"name": "태국의_총리", "id": 46562}, {"name": "프랑스의_총리", "id": 47750}, {"name": "인도의_총리", "id": 50565}, {"name": "이스라엘의_총리", "id": 61091}, {"name": "불가리아의_총리", "id": 64180}, {"name": "튀르키예의_총리", "id": 67171}, {"name": "루마니아의_총리", "id": 69834}, {"name": "스웨덴의_총리", "id": 99403}, {"name": "이탈리아의_총리", "id": 106536}, {"name": "스페인의_총리", "id": 127426}, {"name": "파키스탄의_총리", "id": 155247}, {"name": "캐나다의_총리", "id": 156343}, {"name": "노르웨이의_총리", "id": 206646}, {"name": "덴마크의_총리", "id": 236978}, {"name": "핀란드의_총리", "id": 253475}, {"name": "벨기에의_총리", "id": 277923}, {"name": "그리스의_총리", "id": 318683}, {"name": "이란의_총리", "id": 345218}, {"name": "헝가리의_총리", "id": 364737}, {"name": "네덜란드의_총리", "id": 377898}, {"name": "스리랑카의_총리", "id": 440376}, {"name": "에스토니아의_총리", "id": 608723}, {"name": "카자흐스탄의_총리", "id": 608791}, {"name": "리투아니아의_총리", "id": 667743}, {"name": "중화민국의_행정원장", "id": 1912983}, {"name": "유군", "id": 487128}, {"name": "노르드인_군주", "id": 1481699}, {"name": "무슬림_통치자", "id": 1487102}, {"name": "아돌프_히틀러", "id": 431126}, {"name": "혁명", "id": 33196}, {"name": "쿠데타", "id": 35469}, {"name": "민주화", "id": 1071099}, {"name": "탄핵_절차가_진행된_공직자", "id": 363187}, {"name": "오스만_제국의_군주", "id": 46595}, {"name": "여자_총리", "id": 1893565}, {"name": "캐나다의_총독", "id": 571964}, {"name": "대만_총독", "id": 571968}, {"name": "신화의_왕", "id": 1705004}, {"name": "조선민주주의인민공화국의_중앙_행정기관", "id": 397110}, {"name": "세속주의", "id": 50747}, {"name": "종교와_정치", "id": 463407}, {"name": "기원전_22세기_통치자", "id": 2033695}, {"name": "기원전_6세기_통치자", "id": 2033715}, {"name": "기원전_5세기_통치자", "id": 2033716}, {"name": "기원전_4세기_통치자", "id": 2033717}, {"name": "기원전_3세기_통치자", "id": 2033718}, {"name": "기원전_2세기_통치자", "id": 2033719}, {"name": "기원전_1세기_통치자", "id": 2033720}, {"name": "고대의_유군", "id": 1808304}, {"name": "러시아의_우크라이나_침공에서_러시아가_저지른_전쟁_범죄", "id": 3205566}, {"name": "아이티의_대통령", "id": 426274}, {"name": "대만의_범죄인", "id": 848353}, {"name": "인권", "id": 44037}, {"name": "신분증", "id": 92839}, {"name": "조선의_왕비", "id": 79197}, {"name": "고려의_왕비", "id": 100920}, {"name": "신라의_왕비", "id": 409998}, {"name": "조선의_추존왕후", "id": 1906479}, {"name": "로마법", "id": 273984}, {"name": "로마_제국의_속주", "id": 2882363}, {"name": "브리타니아", "id": 720118}, {"name": "이탈리아의_로마_도시", "id": 3332191}, {"name": "캄파니아주의_로마_유적", "id": 3673380}, {"name": "라치오주의_로마_유적", "id": 3673381}, {"name": "헌정위기", "id": 1839296}, {"name": "미국의_부통령", "id": 12484}, {"name": "미국의_상원의원_선거", "id": 913734}, {"name": "미국_상원_임시의장", "id": 1494101}, {"name": "국방부", "id": 658434}]}