{"name": "스포츠_문화", "id": 213737, "predecessors": [{"name": "하위문화", "id": 85356}, {"name": "문화", "id": 11876}, {"name": "생활", "id": 15596}], "successors": [{"name": "스포츠_게임", "id": 74175}, {"name": "스포츠_만화", "id": 456564}, {"name": "스포츠_애니메이션", "id": 456565}, {"name": "축구_게임", "id": 145266}, {"name": "축구_영화", "id": 377351}, {"name": "축구_만화", "id": 456562}, {"name": "축구_애니메이션", "id": 456563}, {"name": "야구_만화", "id": 456567}, {"name": "야구_애니메이션", "id": 456568}, {"name": "경주_게임", "id": 457718}, {"name": "자동차_경주_영화", "id": 458220}, {"name": "대한민국의_스포츠_드라마", "id": 1748891}, {"name": "일본의_스포츠_드라마", "id": 1748901}, {"name": "대한민국의_고교_야구_대회", "id": 227530}, {"name": "대한민국의_고등학교_야구부", "id": 648632}, {"name": "세계_반도핑_기구_금지_약물", "id": 2965058}, {"name": "도핑_위반_육상_선수", "id": 901090}, {"name": "도핑_위반_수영_선수", "id": 901091}, {"name": "도핑_위반_사이클_선수", "id": 901092}, {"name": "도핑_위반_축구_선수", "id": 901093}, {"name": "도핑_위반_야구_선수", "id": 901116}, {"name": "도핑_위반_종합격투기_선수", "id": 906708}, {"name": "도핑_위반_역도_선수", "id": 1317195}, {"name": "권투_영화", "id": 746538}, {"name": "야구_게임", "id": 288918}, {"name": "대한민국의_고등학교_탁구부", "id": 1110079}, {"name": "아시아의_U-23_축구_국가대표팀", "id": 1239465}, {"name": "대한민국_U-20_축구_국가대표팀_감독", "id": 1871291}, {"name": "대한민국_남자_U-20_축구_국가대표팀_선수", "id": 1871295}, {"name": "대한민국_남자_U-17_축구_국가대표팀_선수", "id": 1871297}, {"name": "응원가", "id": 587538}, {"name": "미국_야구_명예의_전당_헌액자", "id": 284171}, {"name": "일본_야구전당_헌액자", "id": 651979}, {"name": "청소년_야구_대회", "id": 3769217}, {"name": "러시아의_도핑_위반_선수", "id": 901131}, {"name": "대한민국의_고등학교_축구단", "id": 3127586}, {"name": "대한민국의_고등학교_농구부", "id": 650169}, {"name": "대한민국의_아마추어_축구단", "id": 3107232}, {"name": "K3리그_(아마추어)_구단", "id": 1271959}, {"name": "대한민국의_세미프로_축구단", "id": 2394571}, {"name": "전미_농구_협회", "id": 107905}, {"name": "내셔널_하키_리그", "id": 845400}, {"name": "전미_여자_농구_협회", "id": 845403}, {"name": "아메리칸_하키_리그", "id": 1411039}, {"name": "ECHL", "id": 1411883}, {"name": "서던_프로페셔널_하키_리그", "id": 1413011}, {"name": "센트럴_하키_리그", "id": 1413402}, {"name": "아메리칸_농구_협회", "id": 1415222}, {"name": "인터내셔널_하키_리그", "id": 1437883}, {"name": "월드_하키_협회", "id": 1658246}, {"name": "캐나디안_풋볼_리그", "id": 1416322}, {"name": "내셔널_바스켓볼_리그_오브_캐나다_팀", "id": 1430608}, {"name": "AFC_U-16_챔피언십", "id": 360138}, {"name": "FIFA_U-17_월드컵", "id": 126926}, {"name": "AFC_U-19_챔피언십", "id": 521890}, {"name": "FIFA_U-20_월드컵", "id": 138894}, {"name": "UEFA_U-21_축구_선수권_대회", "id": 1396828}, {"name": "대한민국_남자_U-14_축구_국가대표팀_선수", "id": 3002537}, {"name": "2014년_AFC_U-14_챔피언십_참가_선수", "id": 3625217}, {"name": "승부조작", "id": 756890}]}