{"name": "항공기", "id": 30021, "predecessors": [{"name": "탈것", "id": 41512}, {"name": "항공", "id": 40994}], "successors": [{"name": "무인_항공기", "id": 45623}, {"name": "항공기_부품", "id": 51316}, {"name": "항공전자", "id": 108110}, {"name": "헬리콥터", "id": 51804}, {"name": "보잉_항공기", "id": 669396}, {"name": "에어버스_항공기", "id": 669429}, {"name": "수호이_항공기", "id": 669435}, {"name": "야코블레프_항공기", "id": 669598}, {"name": "안토노프_항공기", "id": 732752}, {"name": "더글러스_항공기", "id": 789619}, {"name": "록히드_항공기", "id": 817705}, {"name": "미그기", "id": 1714310}, {"name": "NASA의_항공기", "id": 3756144}, {"name": "비행정", "id": 1032635}, {"name": "1935년_첫_비행한_항공기", "id": 2293126}, {"name": "1940년_첫_비행한_항공기", "id": 2293131}]}