{"name": "15세기_사망", "id": 34400, "predecessors": [{"name": "시간", "id": 31936}, {"name": "죽은_사람", "id": 729802}], "successors": [{"name": "1500년_사망", "id": 24601}, {"name": "1481년_사망", "id": 24640}, {"name": "1406년_사망", "id": 24805}, {"name": "1402년_사망", "id": 24813}, {"name": "1418년_사망", "id": 24779}, {"name": "1425년_사망", "id": 24763}, {"name": "1424년_사망", "id": 24766}, {"name": "1435년_사망", "id": 24740}, {"name": "1440년_사망", "id": 24730}, {"name": "1457년_사망", "id": 24689}, {"name": "1456년_사망", "id": 24692}, {"name": "1453년_사망", "id": 24699}, {"name": "1450년_사망", "id": 24705}, {"name": "1464년_사망", "id": 24674}, {"name": "1463년_사망", "id": 24676}, {"name": "1478년_사망", "id": 24646}, {"name": "1476년_사망", "id": 24650}, {"name": "1471년_사망", "id": 24660}, {"name": "1494년_사망", "id": 24613}]}