{"name": "자살", "id": 34591, "predecessors": [{"name": "사인별_죽음", "id": 119637}, {"name": "사회_문제", "id": 472456}, {"name": "살인", "id": 44019}, {"name": "윤리학_주제", "id": 460176}, {"name": "의료_윤리", "id": 43695}, {"name": "정신건강", "id": 677566}], "successors": [{"name": "자살한_사람", "id": 38953}, {"name": "자살을_소재로_한_작품", "id": 784002}, {"name": "자살_공격", "id": 686635}, {"name": "1945년_자살", "id": 3706598}, {"name": "2011년_자살", "id": 3706666}, {"name": "2019년_자살", "id": 3706674}, {"name": "2020년_자살", "id": 3706675}]}