{"name": "프랑스의_행정_구역", "id": 41321, "predecessors": [{"name": "행정_구역", "id": 30195}, {"name": "G20_회원국", "id": 483843}, {"name": "대륙", "id": 11805}], "successors": [{"name": "프랑스의_주", "id": 42524}, {"name": "프랑스의_코뮌_목록", "id": 656621}, {"name": "앵주의_코뮌", "id": 650994}, {"name": "피니스테르주의_코뮌", "id": 685575}, {"name": "부슈뒤론주의_코뮌", "id": 717516}, {"name": "알프마리팀주의_코뮌", "id": 774006}, {"name": "오드센주의_코뮌", "id": 779780}, {"name": "바르주의_코뮌", "id": 792982}, {"name": "센생드니주의_코뮌", "id": 794705}, {"name": "발드마른주의_코뮌", "id": 809600}, {"name": "파드칼레주의_코뮌", "id": 855493}, {"name": "이블린주의_코뮌", "id": 1013606}, {"name": "노르주의_코뮌", "id": 2397057}, {"name": "발두아즈주의_코뮌", "id": 2397068}, {"name": "센에마른주의_코뮌", "id": 2397069}, {"name": "에손주의_코뮌", "id": 2397070}, {"name": "지롱드주의_코뮌", "id": 2397082}, {"name": "리옹_출신", "id": 651608}, {"name": "오를레앙_공작", "id": 593768}, {"name": "툴루즈_출신", "id": 651610}]}