{"name": "국제_스포츠_대회", "id": 491294, "predecessors": [{"name": "국제_교류", "id": 579355}, {"name": "지구", "id": 30580}, {"name": "문화", "id": 11876}], "successors": [{"name": "팬아메리칸_게임", "id": 665275}, {"name": "나라별_개최된_국제_스포츠_대회_둘러보기_틀", "id": 1677959}, {"name": "퍼시픽_게임", "id": 1720604}, {"name": "동계_유니버시아드", "id": 618332}, {"name": "미국에서_개최된_국제_스포츠_대회", "id": 779380}, {"name": "일본에서_개최된_국제_스포츠_대회", "id": 779843}, {"name": "이탈리아에서_개최된_국제_스포츠_대회", "id": 779862}, {"name": "대한민국에서_개최된_국제_스포츠_대회", "id": 779899}, {"name": "중국에서_개최된_국제_스포츠_대회", "id": 779911}, {"name": "태국에서_개최된_국제_스포츠_대회", "id": 1077187}, {"name": "우루과이에서_개최된_국제_축구_대회", "id": 1077060}, {"name": "UEFA_유로_2012_참가_선수", "id": 798793}, {"name": "UEFA_유로_2012_참가_감독", "id": 1502918}, {"name": "1992년_킹_파흐드컵_참가_선수", "id": 1396703}, {"name": "1995년_킹_파흐드컵_참가_선수", "id": 1396704}, {"name": "1997년_FIFA_컨페더레이션스컵_참가_선수", "id": 1144731}, {"name": "2010년_FIFA_월드컵", "id": 125201}, {"name": "2009년_FIFA_컨페더레이션스컵_참가_선수", "id": 477300}, {"name": "2013년_아프리카_네이션스컵_참가_선수", "id": 1059801}, {"name": "카타르에서_개최된_국제_축구_대회", "id": 1077149}, {"name": "2006년_아시안_게임_참가_선수", "id": 838725}, {"name": "2006년_아시안_게임_경기_종목", "id": 1078943}, {"name": "2006년_아시안_게임_메달리스트", "id": 1173628}, {"name": "아랍에미리트에서_개최된_국제_축구_대회", "id": 1077158}, {"name": "2000년_아프리카_네이션스컵_참가_선수", "id": 1144815}, {"name": "1962년_FIFA_월드컵_참가_선수", "id": 125210}, {"name": "1991년_코파_아메리카_참가_선수", "id": 1144725}, {"name": "2015년_코파_아메리카_참가_선수", "id": 1311924}, {"name": "2015년_유러피언_게임_메달리스트", "id": 2816922}, {"name": "2019년_유러피언_게임_메달리스트", "id": 2994935}, {"name": "2023년_유러피언_게임_메달리스트", "id": 3651601}, {"name": "유러피언_게임_태권도_메달리스트", "id": 2816872}, {"name": "유러피언_게임_레슬링_메달리스트", "id": 2820701}, {"name": "유러피언_게임_사격_메달리스트", "id": 2820704}, {"name": "유러피언_게임_유도_메달리스트", "id": 2820707}, {"name": "유러피언_게임_체조_메달리스트", "id": 2820708}, {"name": "유러피언_게임_펜싱_메달리스트", "id": 2820711}, {"name": "유러피언_게임_육상_메달리스트", "id": 2820733}, {"name": "유러피언_게임_복싱_메달리스트", "id": 2820735}, {"name": "프랑스의_유러피언_게임_금메달리스트", "id": 2821365}, {"name": "이탈리아의_유러피언_게임_금메달리스트", "id": 2821390}, {"name": "2015년_유러피언_게임_태권도_참가_선수", "id": 2816686}, {"name": "2015년_유러피언_게임_사격_참가_선수", "id": 2994940}, {"name": "2019년_유러피언_게임_사격_참가_선수", "id": 2994942}, {"name": "2023년_유러피언_게임_사격_참가_선수", "id": 3651608}, {"name": "2019년_유러피언_게임_양궁_참가_선수", "id": 2994949}, {"name": "2019년_유러피언_게임_복싱_참가_선수", "id": 2994970}, {"name": "2015년_유러피언_게임_펜싱_참가_선수", "id": 2994987}, {"name": "2023년_유러피언_게임_펜싱_참가_선수", "id": 3651619}, {"name": "2015년_유러피언_게임_유도_참가_선수", "id": 2994996}, {"name": "2019년_유러피언_게임_유도_참가_선수", "id": 2994998}, {"name": "2015년_유러피언_게임_레슬링_참가_선수", "id": 2995015}, {"name": "2019년_유러피언_게임_레슬링_참가_선수", "id": 2995017}, {"name": "아시아_선수권_대회", "id": 925225}, {"name": "2023년_유러피언_게임_복싱_참가_선수", "id": 3651607}, {"name": "1982년_코먼웰스_게임_메달리스트", "id": 3880160}, {"name": "1986년_코먼웰스_게임_메달리스트", "id": 3880163}, {"name": "1990년_코먼웰스_게임_메달리스트", "id": 3880167}, {"name": "1994년_코먼웰스_게임_메달리스트", "id": 3880170}, {"name": "1998년_코먼웰스_게임_메달리스트", "id": 3880173}, {"name": "2002년_코먼웰스_게임_메달리스트", "id": 3880176}, {"name": "2006년_코먼웰스_게임_메달리스트", "id": 3880181}, {"name": "2010년_코먼웰스_게임_메달리스트", "id": 3880184}, {"name": "2014년_코먼웰스_게임_메달리스트", "id": 3880187}, {"name": "2018년_코먼웰스_게임_메달리스트", "id": 3880190}, {"name": "2022년_코먼웰스_게임_메달리스트", "id": 3880193}, {"name": "코먼웰스_게임_육상_메달리스트", "id": 3880212}, {"name": "1982년_코먼웰스_게임_육상_참가_선수", "id": 3880279}, {"name": "1986년_코먼웰스_게임_육상_참가_선수", "id": 3880280}, {"name": "1990년_코먼웰스_게임_육상_참가_선수", "id": 3880281}, {"name": "1994년_코먼웰스_게임_육상_참가_선수", "id": 3880282}, {"name": "2002년_코먼웰스_게임_육상_참가_선수", "id": 3880284}, {"name": "2006년_코먼웰스_게임_육상_참가_선수", "id": 3880285}, {"name": "2010년_코먼웰스_게임_육상_참가_선수", "id": 3880286}, {"name": "2014년_코먼웰스_게임_육상_참가_선수", "id": 3880287}, {"name": "2018년_코먼웰스_게임_육상_참가_선수", "id": 3880290}, {"name": "2022년_코먼웰스_게임_육상_참가_선수", "id": 3880291}, {"name": "2006년_코먼웰스_게임_수영_참가_선수", "id": 3880216}, {"name": "2022년_코먼웰스_게임_수영_참가_선수", "id": 3880220}, {"name": "코먼웰스_게임_수영_메달리스트", "id": 3880222}, {"name": "오스트레일리아의_코먼웰스_게임_은메달리스트", "id": 3880530}, {"name": "캐나다의_코먼웰스_게임_은메달리스트", "id": 3880591}, {"name": "잉글랜드의_코먼웰스_게임_은메달리스트", "id": 3880693}, {"name": "2023년_유러피언_게임_육상_참가_선수", "id": 3651602}, {"name": "2023년_유러피언_게임_태권도_참가_선수", "id": 3651617}]}