{"name": "하계_아시안_게임", "id": 548405, "predecessors": [{"name": "아시아의_스포츠_행정_기구", "id": 2964716}], "successors": [{"name": "2014년_아시안_게임_메달리스트", "id": 1173612}, {"name": "2010년_아시안_게임_메달리스트", "id": 1173623}, {"name": "2002년_아시안_게임_메달리스트", "id": 1173627}, {"name": "2006년_아시안_게임_메달리스트", "id": 1173628}, {"name": "1998년_아시안_게임_메달리스트", "id": 1289353}, {"name": "1994년_아시안_게임_메달리스트", "id": 1289367}, {"name": "1990년_아시안_게임_메달리스트", "id": 1289467}, {"name": "1986년_아시안_게임_메달리스트", "id": 1289473}, {"name": "1982년_아시안_게임_메달리스트", "id": 1291039}, {"name": "1978년_아시안_게임_메달리스트", "id": 1291040}, {"name": "1974년_아시안_게임_메달리스트", "id": 1291042}, {"name": "1970년_아시안_게임_메달리스트", "id": 1291046}, {"name": "1962년_아시안_게임_메달리스트", "id": 1291403}, {"name": "1958년_아시안_게임_메달리스트", "id": 1291404}, {"name": "1954년_아시안_게임_메달리스트", "id": 1291405}, {"name": "2018년_아시안_게임_메달리스트", "id": 1979497}, {"name": "2022년_아시안_게임_메달리스트", "id": 3692811}, {"name": "2006년_아시안_게임_참가_선수", "id": 838725}, {"name": "2010년_아시안_게임_참가_선수", "id": 893407}, {"name": "2014년_아시안_게임_참가_선수", "id": 1158549}, {"name": "2002년_아시안_게임_축구_참가_선수", "id": 1179693}, {"name": "2002년_아시안_게임_태권도_참가_선수", "id": 1180043}, {"name": "2002년_아시안_게임_야구_참가_선수", "id": 1180049}, {"name": "2002년_아시안_게임_육상_참가_선수", "id": 1180713}, {"name": "2002년_아시안_게임_유도_참가_선수", "id": 1180716}, {"name": "2002년_아시안_게임_농구_참가_선수", "id": 1180719}, {"name": "2002년_아시안_게임_펜싱_참가_선수", "id": 1180720}, {"name": "2002년_아시안_게임_배구_참가_선수", "id": 1291524}, {"name": "2002년_아시안_게임_탁구_참가_선수", "id": 1652328}, {"name": "1986년_아시안_게임_축구_참가_선수", "id": 1291393}, {"name": "1990년_아시안_게임_축구_참가_선수", "id": 1291392}, {"name": "1954년_아시안_게임_축구_참가_선수", "id": 1291402}, {"name": "1974년_아시안_게임_축구_참가_선수", "id": 1291396}, {"name": "1982년_아시안_게임_축구_참가_선수", "id": 1291394}, {"name": "1978년_아시안_게임_축구_참가_선수", "id": 1291395}, {"name": "1970년_아시안_게임_축구_참가_선수", "id": 1291397}, {"name": "2022년_아시안_게임_축구_참가_선수", "id": 3690735}, {"name": "2022년_아시안_게임_농구_참가_선수", "id": 3690737}, {"name": "2022년_아시안_게임_야구_참가_선수", "id": 3690739}, {"name": "2022년_아시안_게임_육상_참가_선수", "id": 3690753}, {"name": "2022년_아시안_게임_수영_참가_선수", "id": 3690755}, {"name": "2022년_아시안_게임_펜싱_참가_선수", "id": 3690774}]}