{"name": "한국의_음악_장르", "id": 572926, "predecessors": [{"name": "한국의_음악", "id": 11888}, {"name": "예술_장르", "id": 2835674}], "successors": [{"name": "판소리", "id": 154449}, {"name": "한국의_민요", "id": 486402}, {"name": "트로트_노래", "id": 460358}, {"name": "트로트_텔레비전_프로그램", "id": 2683503}, {"name": "대한민국의_힙합_음악가", "id": 300474}, {"name": "대한민국의_힙합_레이블", "id": 583423}, {"name": "대한민국의_힙합댄서", "id": 1623767}, {"name": "K-pop_음반", "id": 610165}, {"name": "K-pop_노래", "id": 976816}, {"name": "대한민국의_재즈_음악가", "id": 467618}, {"name": "대한민국의_음악_순위_텔레비전_프로그램", "id": 490523}]}