{"name": "아시아의_옛_제국", "id": 848407, "predecessors": [{"name": "아시아의_옛_군주국", "id": 848408}, {"name": "아시아의_옛_나라", "id": 12744}, {"name": "옛_제국", "id": 692798}], "successors": [{"name": "대한제국", "id": 14785}, {"name": "몽골_제국", "id": 30409}, {"name": "동로마_제국", "id": 33118}, {"name": "오스만_제국", "id": 39923}, {"name": "러시아_제국", "id": 46605}, {"name": "원나라", "id": 49962}, {"name": "아시리아", "id": 73962}, {"name": "바빌로니아", "id": 99531}, {"name": "킵차크_칸국", "id": 124260}, {"name": "파르티아_제국", "id": 134250}, {"name": "히타이트_제국", "id": 157202}, {"name": "아카드", "id": 174279}, {"name": "아케메네스_제국", "id": 215505}, {"name": "마가다", "id": 424322}, {"name": "일본_제국", "id": 514505}]}